rmw_implementation_cmake/_dummy.cpython-310-x86_64-linux-gnu.so
ros_rmw_implementation_cmake-7.8.2.data/data/share/ament_index/resource_index/package_run_dependencies/rmw_implementation_cmake
ros_rmw_implementation_cmake-7.8.2.data/data/share/ament_index/resource_index/packages/rmw_implementation_cmake
ros_rmw_implementation_cmake-7.8.2.data/data/share/ament_index/resource_index/parent_prefix_path/rmw_implementation_cmake
ros_rmw_implementation_cmake-7.8.2.data/data/share/rmw_implementation_cmake/local_setup.bash
ros_rmw_implementation_cmake-7.8.2.data/data/share/rmw_implementation_cmake/local_setup.dsv
ros_rmw_implementation_cmake-7.8.2.data/data/share/rmw_implementation_cmake/local_setup.sh
ros_rmw_implementation_cmake-7.8.2.data/data/share/rmw_implementation_cmake/local_setup.zsh
ros_rmw_implementation_cmake-7.8.2.data/data/share/rmw_implementation_cmake/package.dsv
ros_rmw_implementation_cmake-7.8.2.data/data/share/rmw_implementation_cmake/package.xml
ros_rmw_implementation_cmake-7.8.2.data/data/share/rmw_implementation_cmake/cmake/ament_cmake_export_dependencies-extras.cmake
ros_rmw_implementation_cmake-7.8.2.data/data/share/rmw_implementation_cmake/cmake/call_for_each_rmw_implementation.cmake
ros_rmw_implementation_cmake-7.8.2.data/data/share/rmw_implementation_cmake/cmake/get_available_rmw_implementations.cmake
ros_rmw_implementation_cmake-7.8.2.data/data/share/rmw_implementation_cmake/cmake/get_default_rmw_implementation.cmake
ros_rmw_implementation_cmake-7.8.2.data/data/share/rmw_implementation_cmake/cmake/rmw_implementation_cmake-extras.cmake
ros_rmw_implementation_cmake-7.8.2.data/data/share/rmw_implementation_cmake/cmake/rmw_implementation_cmakeConfig-version.cmake
ros_rmw_implementation_cmake-7.8.2.data/data/share/rmw_implementation_cmake/cmake/rmw_implementation_cmakeConfig.cmake
ros_rmw_implementation_cmake-7.8.2.data/data/share/rmw_implementation_cmake/environment/ament_prefix_path.dsv
ros_rmw_implementation_cmake-7.8.2.dist-info/METADATA
ros_rmw_implementation_cmake-7.8.2.dist-info/WHEEL
ros_rmw_implementation_cmake-7.8.2.dist-info/top_level.txt
ros_rmw_implementation_cmake-7.8.2.dist-info/RECORD
