Metadata-Version: 2.4
Name: ros-rmw-implementation-cmake
Version: 7.8.2
Summary: This ROS package offers CMake utilities to identify and query available ROS middleware (RMW) implementations.
Dynamic: description
Dynamic: description-content-type
Dynamic: summary
